LICENSE
surv_ai/__init__.py
surv_ai/core/__init__.py
surv_ai/core/agent.py
surv_ai/core/agents/__init__.py
surv_ai/core/agents/binary.py
surv_ai/core/agents/reasoning.py
surv_ai/core/agents/web_page_summary.py
surv_ai/core/interfaces.py
surv_ai/core/model.py
surv_ai/core/survey.py
surv_ai/lib/__init__.py
surv_ai/lib/conversation/__init__.py
surv_ai/lib/conversation/conversation.py
surv_ai/lib/conversation/interfaces.py
surv_ai/lib/knowledge_store/__init__.py
surv_ai/lib/knowledge_store/interfaces.py
surv_ai/lib/knowledge_store/local.py
surv_ai/lib/llm/__init__.py
surv_ai/lib/llm/anthropic.py
surv_ai/lib/llm/gpt.py
surv_ai/lib/llm/interfaces.py
surv_ai/lib/log.py
surv_ai/lib/tools/__init__.py
surv_ai/lib/tools/interfaces.py
surv_ai/lib/tools/query/__init__.py
surv_ai/lib/tools/query/dataframe.py
surv_ai/lib/tools/query/google_custom_search.py
surv_ai/lib/tools/query/twitter.py
surv_ai/lib/tools/query/wikipedia.py
surv_ai/lib/tools/tool.py
surv_ai/lib/tools/tool_belt.py
surv_ai-0.2.0.dist-info/LICENSE
surv_ai-0.2.0.dist-info/METADATA
surv_ai-0.2.0.dist-info/WHEEL
surv_ai-0.2.0.dist-info/RECORD
