Metadata-Version: 2.1
Name: surv-ai
Version: 0.2.0
Summary: A framework for multi-agent modeling using large language models
Home-page: https://github.com/DanielBalsam/surv_ai
License: MIT
Keywords: ai,artificial intelligence,data science,statistics,models,llm,agents,survai,surv_ai,survey,multi-agent,large language model,artificial intelligence,machine learning,natural language processing,nlp,sentiment analysis
Author: Daniel Balsam
Author-email: daniel.balsam@survai.org
Requires-Python: >=3.9,<4.0
Classifier: Development Status :: 3 - Alpha
Classifier: Intended Audience :: Developers
Classifier: License :: OSI Approved :: MIT License
Classifier: Programming Language :: Python :: 3
Classifier: Programming Language :: Python :: 3.9
Classifier: Programming Language :: Python :: 3.10
Classifier: Programming Language :: Python :: 3.11
Requires-Dist: beautifulsoup4 (>=4.12.2,<5.0.0)
Requires-Dist: colorama (>=0.4.6,<0.5.0)
Requires-Dist: exceptiongroup (>=1.1.1,<2.0.0)
Requires-Dist: pydantic (>=1.10.7,<2.0.0)
Requires-Dist: python-dotenv (>=1.0.0,<2.0.0)
Requires-Dist: requests (>=2.31.0,<3.0.0)
Requires-Dist: snscrape @ git+https://github.com/JustAnotherArchivist/snscrape.git
Project-URL: Documentation, https://github.com/DanielBalsam/surv_ai/blob/main/README.md
Project-URL: Repository, https://github.com/DanielBalsam/surv_ai
